setup.py
compass/__init__.py
compass/model.py
compass/ops.py
compass.egg-info/PKG-INFO
compass.egg-info/SOURCES.txt
compass.egg-info/dependency_links.txt
compass.egg-info/not-zip-safe
compass.egg-info/top_level.txt
compass/services/__init__.py
compass/services/bing.py
compass/services/google.py
compass/services/openstreetmap.py
compass/tests/__init__.py
compass/tests/test_queries.py