Metadata-Version: 1.1
Name: compass
Version: 0.1.2
Summary: Compass is a geolocation API client library offering you a flexible set of lookup strategies across a range of web services.
Home-page: https://github.com/Route-Hacker/compass
Author: Matt Rutherford
Author-email: rutherford@clientsideweb.net
License: BSD
Platform: UNKNOWN
Classifier: Development Status :: 4 - Beta
Classifier: Intended Audience :: Developers
Classifier: Natural Language :: English
Classifier: License :: OSI Approved :: BSD License
Classifier: Programming Language :: Python
Classifier: Programming Language :: Python :: 2.7
